scoutpip/.DS_Store
scoutpip/_init_.py
scoutpip/analysis_tools.py
scoutpip/dipole_utilities.py
scoutpip-0.1.5.dist-info/LICENSE
scoutpip-0.1.5.dist-info/METADATA
scoutpip-0.1.5.dist-info/WHEEL
scoutpip-0.1.5.dist-info/RECORD
