Metadata-Version: 2.3
Name: scoutpip
Version: 0.1.5
Summary: Codes necessary for computing the multipoles of the SNe luminosity distance and reproduce the results in https://arxiv.org/pdf/2212.10328, https://arxiv.org/pdf/2403.17741 and https://arxiv.org/pdf/2407.07002
License: GPL-3
Keywords: SNe cosmology,data analysis
Author: Artyom Vorobyov
Author-email: artyom.vorobyov@gmail.com
Requires-Python: >=3.10
Classifier: License :: OSI Approved :: GNU General Public License v3 (GPLv3)
Classifier: License :: Other/Proprietary License
Classifier: Operating System :: OS Independent
Classifier: Programming Language :: Python :: 3
Classifier: Programming Language :: Python :: 3.10
Classifier: Programming Language :: Python :: 3.11
Classifier: Programming Language :: Python :: 3.12
Classifier: Programming Language :: Python :: 3.13
Requires-Dist: astropy (>=5.3.4)
Requires-Dist: emcee (>=3.1.2)
Requires-Dist: getdist (>=1.5.2)
Requires-Dist: matplotlib (>=3.8.0)
Requires-Dist: numpy (>=1.24.3)
Requires-Dist: scipy (>=1.11.4)
Project-URL: Repository, https://github.com/fsorrenti/scout
